arez_currency/__init__.py
arez_currency/core.py
arez_currency/utils.py
arez_currency-1.1.0.dist-info/METADATA
arez_currency-1.1.0.dist-info/WHEEL
arez_currency-1.1.0.dist-info/top_level.txt
arez_currency-1.1.0.dist-info/RECORD
