Metadata-Version: 2.4
Name: arez_currency
Version: 1.1.0
Summary: A simple asynchronous currency, gold, and crypto price fetcher for the Iranian market.
Home-page: https://github.com/amirhossinpython/arez_currency
Author: AmirhosseinPython
Author-email: amirhossinpython03@gmail.com
License: MIT
Project-URL: Source, https://github.com/amirhossinpython/arez_currency
Project-URL: Tracker, https://github.com/amirhossinpython/arez_currency/issues
Keywords: currency,exchange,forex,crypto,Iran,gold,arez_currency,asyncio
Classifier: Programming Language :: Python :: 3
Classifier: License :: OSI Approved :: MIT License
Classifier: Operating System :: OS Independent
Classifier: Topic :: Software Development :: Libraries :: Python Modules
Classifier: Intended Audience :: Developers
Classifier: Natural Language :: Persian
Requires-Python: >=3.8
Requires-Dist: aiohttp>=3.8.0
Requires-Dist: jdatetime>=3.6.0
Requires-Dist: pytz>=2023.0
Dynamic: author
Dynamic: author-email
Dynamic: classifier
Dynamic: description
Dynamic: description-content-type
Dynamic: home-page
Dynamic: keywords
Dynamic: license
Dynamic: project-url
Dynamic: requires-dist
Dynamic: requires-python
Dynamic: summary
